{
	"key" : "enemy_hag15_BABAYAGA",
	"subfolder" : "level15",
	"name" : "BABAYAGA",
	"description" : "Converted from a report",
	"gender" : "NONE",
	"race" : "MONSTER",
	"family" : "mfamily_hag",
	"species" : "BABAYAGA",
	"appearance" : "4dir_ffl2_human",
	"portrait" : "battle_portraits/goblin.png",
	"meatEatLevel" : 15,
	"meatTargetLevel" : 15,
	"gp" : 0,
	"equipped" : [ ],
	"stats" : {
		"hp" : null,
		"mhp" : null,
		"str" : null,
		"def" : null,
		"agi" : null,
		"mana" : null,
		"flags" : null
	}
}