{
	"key" : "enemy_gun09_TROOPER",
	"subfolder" : "level09",
	"name" : "TROOPER",
	"description" : "Converted from a report",
	"gender" : "NONE",
	"race" : "MONSTER",
	"family" : "mfamily_gun",
	"species" : "TROOPER",
	"appearance" : "4dir_ffl2_human",
	"portrait" : "battle_portraits/goblin.png",
	"meatEatLevel" : 0,
	"meatTargetLevel" : 9,
	"gp" : 1200,
	"loot" : null,
	"equipped" : [ ],
	"stats" : {
		"hp" : null,
		"mhp" : null,
		"str" : null,
		"def" : null,
		"agi" : null,
		"mana" : null,
		"flags" : null
	}
}