{
	"key" : "characters_zs2",
	"subfolder" : "",
	"name" : "",
	"description" : "    ",
	"typeName" : [
		{
			"charname" : "HERO",
			"entries" : [
				{
					"fullname" : "Nathaniel Everard the mercenary",
					"charaname" : "Nathaniel"
				},
				{
					"fullname" : "Nathaniel Everard the ex-mercenary",
					"charaname" : "Nathaniel"
				},
				{
					"fullname" : "Nathaniel Everard's time-shifted descendant Oswin Everard",
					"charaname" : "Oswin"
				},
				{
					"fullname" : "exiled Calcedonian prince Luke Lloyd Piedmont",
					"charaname" : "Luke"
				}
			]
		},
		{
			"charname" : "SNARKY",
			"entries" : [
				{
					"fullname" : "Great Sage Kolstya",
					"charaname" : "Kolstya"
				},
				{
					"fullname" : "guildsman Kolstya One-Eye",
					"charaname" : "Kolstya"
				},
				{
					"fullname" : "seer Kyrsta Stormgaze",
					"charaname" : "Kyrsta"
				},
				{
					"fullname" : "diplomat Rachele la Conti",
					"charaname" : "Rachele"
				}
			]
		},
		{
			"charname" : "SECOND",
			"entries" : [
				{
					"fullname" : "Violet",
					"charaname" : "Violet"
				},
				{
					"fullname" : "Violet",
					"charaname" : "Violet"
				},
				{
					"fullname" : "Ace Texel",
					"charaname" : "Ace"
				},
				{
					"fullname" : "Jack Crowley",
					"charaname" : "Jack"
				}
			]
		},
		{
			"charname" : "IDIOT",
			"entries" : [
				{
					"fullname" : "Lord Bismark Turning",
					"charaname" : "Bismark"
				},
				{
					"fullname" : "Lars Thorstrum",
					"charaname" : "Lars"
				},
				{
					"fullname" : "Qetz Xekl",
					"charaname" : "Qetz"
				},
				{
					"fullname" : "Elanna White",
					"charaname" : "Elanna"
				},
				{
					"fullname" : "a robot named Borg Mk.7",
					"charaname" : "Borg"
				}
			]
		},
		{
			"charname" : "EVIL",
			"entries" : [
				{
					"fullname" : "Great Sage Aven",
					"charaname" : "Aven"
				},
				{
					"fullname" : "the ghost of the Great Sage Aven",
					"charaname" : "Aven"
				},
				{
					"fullname" : "The Necromancer Abel",
					"charaname" : "Abel"
				},
				{
					"fullname" : "Aven the Necromancer",
					"charaname" : "Aven"
				},
				{
					"fullname" : "Dark King Reginald Scott Piedmont",
					"charaname" : "Reginald"
				},
				{
					"fullname" : "The Regicide",
					"charaname" : "Regicide"
				}
			]
		}
	]
}